{
  "id": "ea78355c-c492-4b89-8ba0-4ed1bc9b79ad",
  "prevId": "4d5bdedd-30bf-4ccd-98eb-94318de8e4c4",
  "version": "6",
  "dialect": "postgresql",
  "tables": {
    "public.some_data": {
      "name": "some_data",
      "schema": "",
      "columns": {
        "id": {
          "name": "id",
          "type": "varchar",
          "primaryKey": false,
          "notNull": true
        },
        "required": {
          "name": "required",
          "type": "boolean",
          "primaryKey": false,
          "notNull": true
        },
        "number": {
          "name": "number",
          "type": "smallint",
          "primaryKey": false,
          "notNull": true
        }
      },
      "indexes": {},
      "foreignKeys": {},
      "compositePrimaryKeys": {
        "some_data_pk": {
          "name": "some_data_pk",
          "columns": [
            "id"
          ]
        }
      },
      "uniqueConstraints": {}
    },
    "public.tasks": {
      "name": "tasks",
      "schema": "",
      "columns": {
        "id": {
          "name": "id",
          "type": "varchar",
          "primaryKey": false,
          "notNull": true
        },
        "title": {
          "name": "title",
          "type": "varchar",
          "primaryKey": false,
          "notNull": true
        },
        "done": {
          "name": "done",
          "type": "boolean",
          "primaryKey": false,
          "notNull": true
        }
      },
      "indexes": {},
      "foreignKeys": {},
      "compositePrimaryKeys": {},
      "uniqueConstraints": {}
    }
  },
  "enums": {},
  "schemas": {},
  "_meta": {
    "columns": {},
    "schemas": {},
    "tables": {}
  }
}